[
  {
    "id": "129",
    "author": {
      "id": "1",
      "name": "Paul"
    },
    "title": "My awesome blog post",
    "comments": [
      {
        "id": "330",
        "commenter": {
          "id": "2",
          "name": "Nicole"
        }
      }
    ]
  },
  {
    "id": "130",
    "author": {
      "id": "3",
      "name": "Paul"
    },
    "title": "My awesome blog post",
    "comments": [
      {
        "id": "331",
        "commenter": {
          "id": "4",
          "name": "Tom"
        }
      }
    ]
  }
]
